streamlit_user_device/__init__.py
streamlit_user_device/frontend/index.html
streamlit_user_device/frontend/main.js
streamlit_user_device/frontend/streamlit-component-lib.js
streamlit_user_device-0.1.2.dist-info/LICENSE
streamlit_user_device-0.1.2.dist-info/METADATA
streamlit_user_device-0.1.2.dist-info/WHEEL
streamlit_user_device-0.1.2.dist-info/top_level.txt
streamlit_user_device-0.1.2.dist-info/RECORD
