Metadata-Version: 2.1
Name: streamlit-user-device
Version: 0.1.2
Summary: Get User Device
Home-page: https://github.com/phamxtien/streamlit-user-device
Author: Pham Xuan Tien
Author-email: phamxtien@gmail.com
License: UNKNOWN
Platform: UNKNOWN
Requires-Python: >=3.9
License-File: LICENSE
Requires-Dist: streamlit (>=1.15)
